P1_AbrarAfghan/__init__.py
P1_AbrarAfghan/binary_msdsf22m011.py
P1_AbrarAfghan-0.1.dist-info/LICENCE.txt
P1_AbrarAfghan-0.1.dist-info/METADATA
P1_AbrarAfghan-0.1.dist-info/WHEEL
P1_AbrarAfghan-0.1.dist-info/top_level.txt
P1_AbrarAfghan-0.1.dist-info/RECORD
