Metadata-Version: 2.1
Name: P1-AbrarAfghan
Version: 0.1
Summary: Code of Binary search code in Python_Class Assignment
Author: Muhammad Abrar Rahim Afghan
Author-email: abrarkhanafghan@gmail.com
Classifier: Programming Language :: Python :: 3
Classifier: License :: OSI Approved :: MIT License
Classifier: Operating System :: OS Independent
License-File: LICENCE.txt
